setup.py
prettyprint/__init__.py
prettyprint/prettyprint.py
prettyprint.egg-info/PKG-INFO
prettyprint.egg-info/SOURCES.txt
prettyprint.egg-info/dependency_links.txt
prettyprint.egg-info/top_level.txt