Metadata-Version: 1.0
Name: prettyprint
Version: 0.1.5
Summary: prettyprint print list/dict/tuple object prettily
Home-page: http://github.com/taichino/prettyprint
Author: Matsumoto Taichi
Author-email: taichino@gmail.com
License: MIT License
Keywords: pretty print
Platform: UNKNOWN
Classifier: Development Status :: 3 - Alpha
Classifier: Intended Audience :: Developers
Classifier: License :: OSI Approved :: MIT License
Classifier: Operating System :: POSIX
Classifier: Programming Language :: Python
Classifier: Topic :: Software Development :: Libraries :: Python Modules
